sumsy/__init__.py
sumsy/base.py
sumsy/cli.py
sumsy/downloader.py
sumsy/hash.py
sumsy/keygenerator.py
sumsy/signature.py
sumsy/uploader.py
sumsy-0.5.0.dist-info/DESCRIPTION.rst
sumsy-0.5.0.dist-info/METADATA
sumsy-0.5.0.dist-info/RECORD
sumsy-0.5.0.dist-info/WHEEL
sumsy-0.5.0.dist-info/entry_points.txt
sumsy-0.5.0.dist-info/metadata.json
sumsy-0.5.0.dist-info/top_level.txt
