Metadata-Version: 2.0
Name: sumsy
Version: 0.5.0
Summary: A forklift who greatly resembles another forklift
Home-page: https://github.com/biochimia/sumsy
Author: João Abecasis
Author-email: joao@abecasis.name
License: UNKNOWN
Platform: UNKNOWN
Classifier: Development Status :: 3 - Alpha
Classifier: Environment :: Console
Classifier: Intended Audience :: Developers
Classifier: License :: OSI Approved :: Apache Software License
Classifier: Operating System :: OS Independent
Classifier: Programming Language :: Python :: 2.7
Classifier: Programming Language :: Python :: 3.6
Classifier: Topic :: Software Development :: Testing
Classifier: Topic :: System :: Software Distribution
Classifier: Topic :: Utilities
Requires-Dist: boto3 (==1.4.4)
Requires-Dist: botocore (==1.5.65)
Requires-Dist: docutils (==0.13.1)
Requires-Dist: futures (==3.1.1)
Requires-Dist: jmespath (==0.9.3)
Requires-Dist: pycryptodome (==3.4.6)
Requires-Dist: python-dateutil (==2.6.0)
Requires-Dist: s3transfer (==0.1.10)
Requires-Dist: six (==1.10.0)
